libunn/__init__.py
libunn/dice.py
libunn/epoch.py
libunn/log.py
libunn/phrases.py
libunn/spinner.py
libunn/tui.py
libunn-0.2.dist-info/METADATA
libunn-0.2.dist-info/WHEEL
libunn-0.2.dist-info/top_level.txt
libunn-0.2.dist-info/RECORD
