Metadata-Version: 2.2
Name: libunn
Version: 0.2
Summary: Misc scripts that I write
Home-page: https://github.com/juanvel4000/libunn
Author: juanvel400
Author-email: juanvel400@proton.me
Classifier: Programming Language :: Python :: 3
Classifier: License :: OSI Approved :: MIT License
Classifier: Operating System :: OS Independent
Requires-Python: >=3.6
Dynamic: author
Dynamic: author-email
Dynamic: classifier
Dynamic: description
Dynamic: description-content-type
Dynamic: home-page
Dynamic: requires-python
Dynamic: summary
